<?xml version="1.0" encoding="UTF-8"?>
<o><contributors class="object" null="true"/><coordinates class="object" null="true"/><created_at type="string">Thu Mar 25 21:58:13 +0000 2010</created_at><favorited type="boolean">false</favorited><geo class="object" null="true"/><id type="number">11055415162</id><in_reply_to_screen_name class="object" null="true"/><in_reply_to_status_id class="object" null="true"/><in_reply_to_user_id class="object" null="true"/><place class="object" null="true"/><retweeted_status class="object"><contributors class="object" null="true"/><coordinates class="object" null="true"/><created_at type="string">Thu Mar 25 21:56:31 +0000 2010</created_at><favorited type="boolean">false</favorited><geo class="object" null="true"/><id type="number">11055345682</id><in_reply_to_screen_name class="object" null="true"/><in_reply_to_status_id class="object" null="true"/><in_reply_to_user_id class="object" null="true"/><place class="object" null="true"/><source type="string">&lt;a href="http://www.tweetdeck.com" rel="nofollow"&gt;TweetDeck&lt;/a&gt;</source><text type="string">0.1% - this is not a recovery, this is a rounding error #labour #ge10 #gameon</text><truncated type="boolean">false</truncated><user class="object"><contributors_enabled type="boolean">false</contributors_enabled><created_at type="string">Mon Feb 15 18:10:42 +0000 2010</created_at><description type="string">I despise Socialism, I'm sick and tired of being told what to do by Government LEAVE ME ALONE, if I make a mistake - MY FAULT.</description><favourites_count type="number">0</favourites_count><followers_count type="number">93</followers_count><following class="object" null="true"/><friends_count type="number">54</friends_count><geo_enabled type="boolean">false</geo_enabled><id type="number">114522843</id><lang type="string">en</lang><location type="string">People's republic of England</location><name type="string">Heads on poles</name><notifications class="object" null="true"/><profile_background_color type="string">9ae4e8</profile_background_color><profile_background_image_url type="string">http://s.twimg.com/a/1269020849/images/themes/theme1/bg.png</profile_background_image_url><profile_background_tile type="boolean">false</profile_background_tile><profile_image_url type="string">http://a3.twimg.com/profile_images/766323803/twitterProfilePhoto_normal.jpg</profile_image_url><profile_link_color type="string">0000ff</profile_link_color><profile_sidebar_border_color type="string">87bc44</profile_sidebar_border_color><profile_sidebar_fill_color type="string">e0ff92</profile_sidebar_fill_color><profile_text_color type="string">000000</profile_text_color><protected type="boolean">false</protected><screen_name type="string">headsonpoles</screen_name><statuses_count type="number">1417</statuses_count><time_zone type="string">London</time_zone><url class="object" null="true"/><utc_offset type="number">0</utc_offset><verified type="boolean">false</verified></user></retweeted_status><source type="string">&lt;a href="http://www.tweetdeck.com" rel="nofollow"&gt;TweetDeck&lt;/a&gt;</source><text type="string">RT @headsonpoles: 0.1% - this is not a recovery, this is a rounding error #labour #ge10 #gameon</text><truncated type="boolean">false</truncated><user class="object"><contributors_enabled type="boolean">false</contributors_enabled><created_at type="string">Tue Jul 14 08:19:16 +0000 2009</created_at><description type="string">Rightly wry, satirically right</description><favourites_count type="number">27</favourites_count><followers_count type="number">829</followers_count><following class="object" null="true"/><friends_count type="number">771</friends_count><geo_enabled type="boolean">false</geo_enabled><id type="number">56643102</id><lang type="string">en</lang><location type="string">Back Benches</location><name type="string">Parlez~me~'n~Tory</name><notifications class="object" null="true"/><profile_background_color type="string">9AE4E8</profile_background_color><profile_background_image_url type="string">http://a1.twimg.com/profile_background_images/37805578/Picture_009.jpg</profile_background_image_url><profile_background_tile type="boolean">true</profile_background_tile><profile_image_url type="string">http://a1.twimg.com/profile_images/525912284/twitterProfilePhoto_normal.jpg</profile_image_url><profile_link_color type="string">0084B4</profile_link_color><profile_sidebar_border_color type="string">BDDCAD</profile_sidebar_border_color><profile_sidebar_fill_color type="string">DDFFCC</profile_sidebar_fill_color><profile_text_color type="string">333333</profile_text_color><protected type="boolean">false</protected><screen_name type="string">Parlez_me_nTory</screen_name><statuses_count type="number">10788</statuses_count><time_zone type="string">London</time_zone><url type="string">http://www.wicksie.com</url><utc_offset type="number">0</utc_offset><verified type="boolean">false</verified></user></o>
